kaldiadaptlm/__init__.py
kaldiadaptlm/templates/kaldi-run-adaptation.sh
kaldiadaptlm/templates/kaldi-cmd.sh
kaldiadaptlm/templates/kaldi-path.sh.template
kaldiadaptlm/templates/kaldi-model-dist.sh
kaldi_adapt_lm-0.1.3.data/scripts/kaldi-adapt-lm
kaldi_adapt_lm-0.1.3.dist-info/top_level.txt
kaldi_adapt_lm-0.1.3.dist-info/METADATA
kaldi_adapt_lm-0.1.3.dist-info/DESCRIPTION.rst
kaldi_adapt_lm-0.1.3.dist-info/metadata.json
kaldi_adapt_lm-0.1.3.dist-info/WHEEL
kaldi_adapt_lm-0.1.3.dist-info/RECORD
