Metadata-Version: 2.0
Name: kaldi-adapt-lm
Version: 0.1.3
Summary: Adapt Kaldi-ASR nnet3 chain models from Zamia-Speech.org to a different language model.
Home-page: https://github.com/gooofy/kaldi-adapt-lm
Author: Guenter Bartsch
Author-email: guenter@zamia.org
License: Apache
Keywords: natural language processing nlp asr speech recognition kaldi
Platform: UNKNOWN
Classifier: Operating System :: POSIX :: Linux
Classifier: License :: OSI Approved :: Apache Software License
Classifier: Programming Language :: Python :: 2
Classifier: Programming Language :: Python :: 2.7
Classifier: Intended Audience :: Developers
Classifier: Topic :: Software Development :: Libraries :: Python Modules
Classifier: Topic :: Multimedia :: Sound/Audio :: Speech
Classifier: Topic :: Scientific/Engineering :: Artificial Intelligence
Requires-Dist: py-nltools
